colorsep/__init__.py
colorsep/process.py
colorsep-0.0.3.data/data/README.md
colorsep-0.0.3.dist-info/METADATA
colorsep-0.0.3.dist-info/WHEEL
colorsep-0.0.3.dist-info/entry_points.txt
colorsep-0.0.3.dist-info/top_level.txt
colorsep-0.0.3.dist-info/RECORD
