Metadata-Version: 2.1
Name: colorsep
Version: 0.0.3
Summary: a utility for separating images for screen printing
Home-page: https://gitlab.com/frameworklabs/colorsep
Author: Framework Labs
Author-email: fred@frameworklabs.us
License: MIT
Keywords: color separation screen printing
Platform: UNKNOWN
Classifier: Development Status :: 2 - Pre-Alpha
Classifier: Intended Audience :: Developers
Classifier: Topic :: Utilities
Classifier: License :: OSI Approved :: MIT License
Classifier: Programming Language :: Python :: 3
Requires-Dist: Click (==7.0)
Requires-Dist: scipy (==1.1.0)
Requires-Dist: pypng (==0.0.18)
